latest_tag/__init__.py
latest_tag/cli.py
latest_tag-1.0.4.dist-info/entry_points.txt
latest_tag-1.0.4.dist-info/LICENSE
latest_tag-1.0.4.dist-info/METADATA
latest_tag-1.0.4.dist-info/WHEEL
latest_tag-1.0.4.dist-info/RECORD
