Metadata-Version: 2.3
Name: latest_tag
Version: 1.0.4
Summary: Tag fetcher for GitHub releases with optional asset filtering
License: MIT
Keywords: github,releases,cli,automation,tags
Author: Munywele Sammy Barasa
Author-email: sammy@munywele.co.ke
Requires-Python: >=3.12
Classifier: License :: OSI Approved :: MIT License
Classifier: Programming Language :: Python :: 3
Classifier: Programming Language :: Python :: 3.12
Classifier: Programming Language :: Python :: 3.13
Requires-Dist: loguru (>=0.7.2,<1.0.0)
Requires-Dist: pygithub (>=2.6.1,<3.0.0)
Requires-Dist: python-dotenv (>=1.1.1,<2.0.0)
Requires-Dist: requests (>=2.32.4,<3.0.0)
Requires-Dist: typer (>=0.16.0,<0.17.0)
